setuptools_test_command_stub.pth
setuptools_test_command_stub/__init__.py
setuptools_test_command_stub-0.1.2.dist-info/LICENSE
setuptools_test_command_stub-0.1.2.dist-info/METADATA
setuptools_test_command_stub-0.1.2.dist-info/WHEEL
setuptools_test_command_stub-0.1.2.dist-info/RECORD
