Metadata-Version: 2.1
Name: setuptools-test-command-stub
Version: 0.1.2
Summary: Patches setuptools.command.test with mock
Home-page: https://github.com/gtors/setuptools-test-command-stub
License: MIT
Author: Andrey Torsunov
Author-email: andrey.torsunov@gmail.com
Requires-Python: >=3.7,<4.0
Classifier: Development Status :: 5 - Production/Stable
Classifier: License :: OSI Approved :: MIT License
Classifier: Programming Language :: Python :: 3
Classifier: Programming Language :: Python :: 3.7
Classifier: Programming Language :: Python :: 3.8
Classifier: Programming Language :: Python :: 3.9
Classifier: Programming Language :: Python :: 3.10
Classifier: Programming Language :: Python :: 3.11
Classifier: Programming Language :: Python :: 3.12
Project-URL: Repository, https://github.com/gtors/setuptools-test-command-stub
